{
	"peasant": {
		"hp": 25,
		"attack": 10,
		"move_speed": 50.0,
		"attack_speed": 0.8,
		"cost": 5.0,
		"cooldown": 5.0,
		"range": 32.0,
		"sprite_frame": "res://reso/sprites/peasant.tres"
	},
	"warrior": {
		"hp": 25,
		"attack": 10,
		"move_speed": 35.0,
		"attack_speed": 2.0,
		"cost": 25.0,
		"cooldown": 10.0,
		"range": 32.0,
		"sprite_frame": "res://reso/sprites/warrior.tres"
	},
	"hunter": {
		"hp": 25,
		"attack": 10,
		"move_speed": 55.0,
		"attack_speed": 1.0,
		"cost": 10.0,
		"cooldown": 15.0,
		"range": 200.0,
		"sprite_frame": "res://reso/sprites/hunter.tres"
	},
	"swordsman": {
		"hp": 25,
		"attack": 10,
		"move_speed": 30.0,
		"attack_speed": 1.5,
		"cost": 15.0,
		"cooldown": 30.0,
		"range": 32.0,
		"sprite_frame": "res://reso/sprites/swordsman.tres"
	},
	"amazon": {
		"hp": 25,
		"attack": 10,
		"move_speed": 40.0,
		"attack_speed": 2.5,
		"cost": 50.0,
		"cooldown": 60.0,
		"range": 32.0,
		"sprite_frame": "res://reso/sprites/amazon.tres"
	},
	"goblin": {
		"hp": 25,
		"attack": 10,
		"move_speed": 65.0,
		"attack_speed": 1.0,
		"cost": 50.0,
		"cooldown": 60.0,
		"range": 32.0,
		"sprite_frame": "res://reso/sprites/goblin.tres"
	},
	"flying_demon": {
		"hp": 25,
		"attack": 10,
		"move_speed": 40.0,
		"attack_speed": 1.5,
		"cost": 50.0,
		"cooldown": 60.0,
		"range": 32.0,
		"sprite_frame": "res://reso/sprites/flying_demon.tres"
	},
	"mushroom": {
		"hp": 25,
		"attack": 10,
		"move_speed": 25.0,
		"attack_speed": 1.5,
		"cost": 50.0,
		"cooldown": 60.0,
		"range": 32.0,
		"sprite_frame": "res://reso/sprites/mushroom.tres"
	}
}
